nameko_cachetools/__init__.py
nameko_cachetools/nameko_cachetools.py
nameko_cachetools-1.0.0.dist-info/METADATA
nameko_cachetools-1.0.0.dist-info/RECORD
nameko_cachetools-1.0.0.dist-info/WHEEL
nameko_cachetools-1.0.0.dist-info/top_level.txt
